esrinlutils/__init__.py
esrinlutils/utilities.py
esrinlutils-0.6.dist-info/LICENSE
esrinlutils-0.6.dist-info/METADATA
esrinlutils-0.6.dist-info/WHEEL
esrinlutils-0.6.dist-info/top_level.txt
esrinlutils-0.6.dist-info/RECORD
