Metadata-Version: 2.1
Name: esrinlutils
Version: 0.6
Summary: A set of common functions to be used in scripts
Home-page: https://github.com/esrinederland/PythonUtils
Author: EsriNL DevTeam
Author-email: developers@esri.nl
License: MIT
Download-URL: https://github.com/esrinederland/PythonUtils/archive/refs/tags/0.6.tar.gz
Platform: UNKNOWN
